{
  "query": "\"Microsoft\" revenue financials 2024",
  "query_hash": "1ba06db0273d026a",
  "results": {
    "query": "\"Microsoft\" revenue financials 2024",
    "follow_up_questions": null,
    "answer": null,
    "images": [],
    "results": [
      {
        "url": "https://www.macrotrends.net/stocks/charts/MSFT/microsoft/revenue",
        "title": "Microsoft Revenue 2011-2025 | MSFT - Macrotrends",
        "content": "* Microsoft annual revenue for 2025 was **$281.724B**, a **14.93% increase** from 2024. * Microsoft annual revenue for 2024 was **$245.122B**, a **15.67% increase** from 2023. * Microsoft annual revenue for 2023 was **$211.915B**, a **6.88% increase** from 2022. | Adobe (ADBE) | United States | $133.420B | 19.04 | | Cadence Design Systems (CDNS) | United States | $82.877B | 56.28 | | CommVault Systems (CVLT) | United States | $5.295B | 57.46 | | Progress Software (PRGS) | United States | $1.719B | 9.02 | | Verint Systems (VRNT) | United States | $1.226B | 16.06 | | NetSol Technologies (NTWK) | United States | $0.036B | 75.25 | | Smith Micro Software (SMSI) | United States | $0.013B | 0.00 |",
        "score": 0.921591,
        "raw_content": null
      },
      {
        "url": "https://www.microsoft.com/investor/reports/ar24/",
        "title": "Microsoft 2024 Annual Report",
        "content": "[Microsoft Annual Report 2024](https://www.microsoft.com/investor/reports/ar24/#home) *   [Home](https://www.microsoft.com/investor/reports/ar24/#home) *   [Shareholder Letter](https://www.microsoft.com/investor/reports/ar24/#shareholder-letter) *   [Financial Review](https://www.microsoft.com/investor/reports/ar24/#financial-review) *   [Financial Review](https://www.microsoft.com/investor/reports/ar24/#financial-review) *   [Business](https://www.microsoft.com/investor/reports/ar24/#business-description) *   [Business](https://www.microsoft.com/investor/reports/ar24/#business-description) *   [General](https://www.microsoft.com/investor/reports/ar24/#general) *   [Human Capital Resources](https://www.microsoft.com/investor/reports/ar24/#human-capital-resources) *   [Operating Segments](https://www.microsoft.com/investor/reports/ar24/#operating-segments) *   [Operations](https://www.microsoft.com/investor/reports/ar24/#operations) *   [Research & Development](https://www.microsoft.com/investor/reports/ar24/#research-development) *   [Distribution, Sales & Marketing](https://www.microsoft.com/investor/reports/ar24/#distribution-sales-marketing) *   [Licensing Options](https://www.microsoft.com/investor/reports/ar24/#licensing-options) *   [Customers](https://www.microsoft.com/investor/reports/ar24/#customers) *   [Government Regulation](https://www.microsoft.com/investor/reports/ar24/#government-regulation) *   [Available Information](https://www.microsoft.com/investor/reports/ar24/#available-information) *   [Discussion & Analysis](https://www.microsoft.com/investor/reports/ar24/#discussion-analysis) *   [Market Risk](https://www.microsoft.com/investor/reports/ar24/#market-risk) *   [Income Statements](https://www.microsoft.com/investor/reports/ar24/#income-statements) *   [Balance Sheets](https://www.microsoft.com/investor/reports/ar24/#balance-sheets) *   [Cash Flows Statements](https://www.microsoft.com/investor/reports/ar24/#cash-flows-statements) *   [Stockholders' Equity](https://www.microsoft.com/investor/reports/ar24/#stockholders-equity) *   [Notes](https://www.microsoft.com/investor/reports/ar24/#accounting-policies) *   [Notes](https://www.microsoft.com/investor/reports/ar24/#accounting-policies) *   [Accounting Policies](https://www.microsoft.com/investor/reports/ar24/#accounting-policies) *   [Earnings Per Share](https://www.microsoft.com/investor/reports/ar24/#earnings-per-share) *   [Other Income (Expense), Net](https://www.microsoft.com/investor/reports/ar24/#other-income) *   [Investments](https://www.microsoft.com/investor/reports/ar24/#investments) *   [Derivatives](https://www.microsoft.com/investor/reports/ar24/#derivatives) *   [Inventories](https://www.microsoft.com/investor/reports/ar24/#inventories) *   [Property and Equipment](https://www.microsoft.com/investor/reports/ar24/#property-equipment) *   [Business Combinations](https://www.microsoft.com/investor/reports/ar24/#business-combinations) *   [Goodwill](https://www.microsoft.com/investor/reports/ar24/#goodwill) *   [Intangible Assets](https://www.microsoft.com/investor/reports/ar24/#intangible-assets) *   [Debt](https://www.microsoft.com/investor/reports/ar24/#debt) *   [Income Taxes](https://www.microsoft.com/investor/reports/ar24/#income-taxes) *   [Unearned Revenue](https://www.microsoft.com/investor/reports/ar24/#unearned-revenue) *   [Leases](https://www.microsoft.com/investor/reports/ar24/#leases) *   [Contingencies](https://www.microsoft.com/investor/reports/ar24/#contingencies) *   [Stockholders' Equity](https://www.microsoft.com/investor/reports/ar24/#stockholders-equity-2) *   [Accumulated Other Comprehensive Income (Loss)](https://www.microsoft.com/investor/reports/ar24/#accumulated-other-comprehensive-income) *   [Employee Stock and Savings Plans](https://www.microsoft.com/investor/reports/ar24/#employee-stock-savings-plans) *   [Segment Information & Geo Data](https://www.microsoft.com/investor/reports/ar24/#segment-information-geo-data) *   [Auditor's Report](https://www.microsoft.com/investor/reports/ar24/#auditors-report) *   [Controls & Procedures](https://www.microsoft.com/investor/reports/ar24/#controls-procedures) *   [Directors & Officers](https://www.microsoft.com/investor/reports/ar24/#directors-and-officers) *   [Investor Relations](https://www.microsoft.com/investor/reports/ar24/#investor-relations) [Continue to Shareholder Letter](https://www.microsoft.com/investor/reports/ar24/#) *   [Download Center](https://www.microsoft.com/investor/reports/ar24/download-center/index.html)",
        "score": 0.92005306,
        "raw_content": null
      },
      {
        "url": "https://www.microsoft.com/en-us/investor/earnings/fy-2024-q4/segment-revenues",
        "title": "FY24 Q4 - Segment Revenue and Operating Income - Microsoft",
        "content": "# Earnings Release FY24 Q4 ## Segment Revenue and Operating Income *IMPORTANT NOTICE TO USERS (summary only, click here  for full text of notice);*All information is unaudited unless otherwise noted or accompanied by an audit opinion and is subject to the more comprehensive information contained in our SEC reports and filings. All information speaks as of the last fiscal quarter or year for which we have filed a Form 10-K or 10-Q, or for historical information the date or period expressly indicated in or with such information. ### Download Earnings Related Files Information contained in these documents is current as of the earnings date, and not restated for new accounting standards #### Earnings Release Pages #### Related Information",
        "score": 0.8405867,
        "raw_content": null
      }
    ],
    "response_time": 0.92,
    "request_id": "fafec637-ee08-43df-8d4b-e1864b2126b0"
  },
  "timestamp": "2025-12-08T01:23:35.388657",
  "expires": "2025-12-15T01:23:35.388657",
  "source_count": 3
}