{
  "company": "Microsoft",
  "generated_at": "2025-12-09T00:03:28.438224",
  "profile": {
    "legal_name": "Microsoft Corporation",
    "ticker": "MSFT",
    "exchange": "NASDAQ",
    "industry": "Technology",
    "country": "United States"
  },
  "research": {
    "quality_score": 90.0,
    "depth": "comprehensive",
    "iteration_count": 1,
    "sources_count": 37
  },
  "financial_data_available": true,
  "extracted_metrics": {
    "market_cap_text": "$3.59T",
    "revenue_text": "$261.8B",
    "employees": 221000,
    "employees_text": "221,000"
  }
}