{
  "company": "America Movil",
  "generated_at": "2025-12-09T00:33:46.198375",
  "profile": {
    "legal_name": "America Movil, S.A.B. de C.V.",
    "ticker": "",
    "exchange": "",
    "industry": "Telecommunications",
    "country": "Mexico"
  },
  "research": {
    "quality_score": 70.0,
    "depth": "comprehensive",
    "iteration_count": 1,
    "sources_count": 0
  },
  "financial_data_available": false,
  "extracted_metrics": {
    "employees": 180000,
    "employees_text": "180,000"
  }
}